lfdfiles/__init__.py
lfdfiles/__main__.py
lfdfiles/lfdfiles.py
lfdfiles/py.typed
lfdfiles-2026.1.14.dist-info/licenses/LICENSE
lfdfiles-2026.1.14.dist-info/METADATA
lfdfiles-2026.1.14.dist-info/WHEEL
lfdfiles-2026.1.14.dist-info/entry_points.txt
lfdfiles-2026.1.14.dist-info/top_level.txt
lfdfiles-2026.1.14.dist-info/zip-safe
lfdfiles-2026.1.14.dist-info/RECORD
