Metadata-Version: 2.4
Name: lfdfiles
Version: 2026.1.14
Summary: Laboratory for Fluorescence Dynamics (LFD) file formats
Home-page: https://www.cgohlke.com
Author: Christoph Gohlke
Author-email: cgohlke@cgohlke.com
License: BSD-3-Clause
Project-URL: Bug Tracker, https://github.com/cgohlke/lfdfiles/issues
Project-URL: Source Code, https://github.com/cgohlke/lfdfiles
Platform: any
Classifier: Development Status :: 4 - Beta
Classifier: Intended Audience :: Science/Research
Classifier: Intended Audience :: Developers
Classifier: Operating System :: OS Independent
Classifier: Programming Language :: Python :: 3 :: Only
Classifier: Programming Language :: Python :: 3.11
Classifier: Programming Language :: Python :: 3.12
Classifier: Programming Language :: Python :: 3.13
Classifier: Programming Language :: Python :: 3.14
Requires-Python: >=3.11
License-File: LICENSE
Requires-Dist: numpy
Requires-Dist: tifffile
Requires-Dist: click
Provides-Extra: all
Requires-Dist: imagecodecs; extra == "all"
Requires-Dist: matplotlib; extra == "all"
Requires-Dist: fbdfile; extra == "all"
Requires-Dist: czifile; extra == "all"
Requires-Dist: oiffile; extra == "all"
Requires-Dist: netpbmfile; extra == "all"
Dynamic: author
Dynamic: author-email
Dynamic: classifier
Dynamic: description
Dynamic: description-content-type
Dynamic: home-page
Dynamic: license
Dynamic: license-file
Dynamic: platform
Dynamic: project-url
Dynamic: provides-extra
Dynamic: requires-dist
Dynamic: requires-python
Dynamic: summary
